jwsoup/__init__.py
jwsoup/package_metadata.py
jwsoup/audio/__init__.py
jwsoup/audio/downloader.py
jwsoup/audio/extractor.py
jwsoup/audio/scraper.py
jwsoup/audio/utils.py
jwsoup/text/__init__.py
jwsoup/text/scraper.py
jwsoup/text/utils.py
jwsoup-0.1.1.dist-info/LICENSE
jwsoup-0.1.1.dist-info/METADATA
jwsoup-0.1.1.dist-info/WHEEL
jwsoup-0.1.1.dist-info/top_level.txt
jwsoup-0.1.1.dist-info/RECORD
