Metadata-Version: 2.2
Name: jwsoup
Version: 0.1.1
Summary: This package is design to scrape Bible data on JW.org for NLP/IAgen task.
Home-page: https://github.com/sawadogosalif/jwsoup.git
Author: Salif SAWADOGO
Author-email: salif.sawadogo.pro@gmail.com
Keywords: jwsoup
Classifier: Programming Language :: Python :: 3
Classifier: License :: OSI Approved :: MIT License
Classifier: Operating System :: OS Independent
Requires-Python: >=3.8
License-File: LICENSE
Requires-Dist: requests>=2.0.0
Requires-Dist: beautifulsoup4>=4.9.0
Requires-Dist: loguru>=0.5.0
Requires-Dist: pandas>=1.0.0
Requires-Dist: pyarrow>=10.0.0
Requires-Dist: beartype>=0.17.0
Dynamic: author
Dynamic: author-email
Dynamic: classifier
Dynamic: description
Dynamic: description-content-type
Dynamic: home-page
Dynamic: keywords
Dynamic: requires-dist
Dynamic: requires-python
Dynamic: summary
